CHANGELOG.rst
LICENSE.txt
MANIFEST.in
README.rst
setup.py
dms_tools.egg-info/PKG-INFO
dms_tools.egg-info/SOURCES.txt
dms_tools.egg-info/dependency_links.txt
dms_tools.egg-info/requires.txt
dms_tools.egg-info/top_level.txt
docs/Makefile
docs/README.rst
docs/algorithms.rst
docs/alignmentsummary_barcodes.pdf
docs/alignmentsummary_depth.pdf
docs/alignmentsummary_mutcounts_all.pdf
docs/alignmentsummary_mutcounts_multi_nt.pdf
docs/alignmentsummary_mutdepth.pdf
docs/alignmentsummary_mutfreqs.pdf
docs/alignmentsummary_reads.pdf
docs/alignmentsummary_singlemuttypes.pdf
docs/citations.rst
docs/conf.py
docs/diffprefs_logoplot.pdf
docs/diffsel_logoplot.pdf
docs/dms_barcodedsubamplicons.rst
docs/dms_correlate.rst
docs/dms_diffselection.rst
docs/dms_editsites.rst
docs/dms_inferdiffprefs.rst
docs/dms_inferprefs.rst
docs/dms_logoplot.rst
docs/dms_matchsubassembledbarcodes.rst
docs/dms_merge.rst
docs/dms_subassemble.rst
docs/dms_summarizealignments.rst
docs/examples.rst
docs/fileformats.rst
docs/index.rst
docs/inferdiffprefs_algorithm.rst
docs/inferprefs_algorithm.rst
docs/installation.rst
docs/matchbarcodesummary_allcumulcounts_Lib1.pdf
docs/matchbarcodesummary_allmutdepth_Lib1.pdf
docs/matchbarcodesummary_allmutdepth_Lib1_Input.pdf
docs/matchbarcodesummary_allmutfreqs.pdf
docs/matchbarcodesummary_muts_per_matched_read.pdf
docs/matchbarcodesummary_reads.pdf
docs/matchbarcodesummary_singlecumulcounts_Lib1.pdf
docs/matchbarcodesummary_singlemutdepth_Lib1.pdf
docs/matchbarcodesummary_singlemutfreqs.pdf
docs/pref1_vs_pref2_corr.pdf
docs/prefs_logoplot.pdf
docs/prefs_logoplot_withoverlay.pdf
docs/programs.rst
docs/pythonapi.rst
docs/subassemblysummary_depth.pdf
docs/subassemblysummary_nsubassembled.pdf
docs/subassemblysummary_reads.pdf
docs/weblinks.txt
scripts/dms_barcodedsubamplicons
scripts/dms_correlate
scripts/dms_diffselection
scripts/dms_editsites
scripts/dms_inferdiffprefs
scripts/dms_inferprefs
scripts/dms_logoplot
scripts/dms_matchsubassembledbarcodes
scripts/dms_merge
scripts/dms_subassemble
scripts/dms_summarizealignments
src/__init__.py
src/_metadata.py
src/_weblogo_template.eps
src/cutils.c
src/file_io.py
src/mcmc.py
