Metadata-Version: 1.1
Name: dms-tools
Version: 1.2.1
Summary: Deep mutational scanning (DMS) analysis tools.
Home-page: http://jbloomlab.github.io/dms_tools/
Author: the Bloom Lab (see https://github.com/jbloomlab/dms_tools/graphs/contributors for all contributors)
Author-email: jbloom@fredhutch.org
License: GPLv3
Download-URL: https://github.com/jbloomlab/dms_tools/tarball/1.2.1
Platform: Linux (and maybe also Mac OS X).
